README.md
pyproject.toml
setup.cfg
setup.py
cbcintacctsdk/__init__.py
cbcintacctsdk/exceptions.py
cbcintacctsdk/main.py
cbcintacctsdk.egg-info/PKG-INFO
cbcintacctsdk.egg-info/SOURCES.txt
cbcintacctsdk.egg-info/dependency_links.txt
cbcintacctsdk.egg-info/not-zip-safe
cbcintacctsdk.egg-info/requires.txt
cbcintacctsdk.egg-info/top_level.txt
cbcintacctsdk/apis/__init__.py
cbcintacctsdk/apis/accounts.py
cbcintacctsdk/apis/ap_payments.py
cbcintacctsdk/apis/api_base.py
cbcintacctsdk/apis/ar_adjustment.py
cbcintacctsdk/apis/ar_invoices.py
cbcintacctsdk/apis/attachments.py
cbcintacctsdk/apis/bills.py
cbcintacctsdk/apis/charge_card_accounts.py
cbcintacctsdk/apis/charge_card_transactions.py
cbcintacctsdk/apis/checking_accounts.py
cbcintacctsdk/apis/classes.py
cbcintacctsdk/apis/constants.py
cbcintacctsdk/apis/contacts.py
cbcintacctsdk/apis/custom_reports.py
cbcintacctsdk/apis/customer_types.py
cbcintacctsdk/apis/customers.py
cbcintacctsdk/apis/departments.py
cbcintacctsdk/apis/dimension_values.py
cbcintacctsdk/apis/dimensions.py
cbcintacctsdk/apis/employees.py
cbcintacctsdk/apis/expense_payment_types.py
cbcintacctsdk/apis/expense_reports.py
cbcintacctsdk/apis/expense_types.py
cbcintacctsdk/apis/gl_detail.py
cbcintacctsdk/apis/invoices.py
cbcintacctsdk/apis/items.py
cbcintacctsdk/apis/location_entities.py
cbcintacctsdk/apis/locations.py
cbcintacctsdk/apis/projects.py
cbcintacctsdk/apis/read_report.py
cbcintacctsdk/apis/reimbursements.py
cbcintacctsdk/apis/savings_accounts.py
cbcintacctsdk/apis/tasks.py
cbcintacctsdk/apis/tax_details.py
cbcintacctsdk/apis/vendors.py