Metadata-Version: 1.2
Name: cbcintacctsdk
Version: 0.0.17
Summary: Forked Python SDK for accessing Sage Intacct APIs
Home-page: https://github.com/Cold-Bore-Capital/sageintacct-sdk-py'
Author: Cold Bore Capital
Author-email: it-group@coldborecapital.com
License: UNKNOWN
Platform: UNKNOWN
Classifier: Programming Language :: Python :: 3.8
Classifier: Topic :: Software Development :: Libraries :: Python Modules
Classifier: Development Status :: 5 - Production/Stable
Requires-Python: >=3.7.1
